SiPM.cpython-36m-darwin.so
SiPM-2.3.1.dist-info/LICENSE
SiPM-2.3.1.dist-info/METADATA
SiPM-2.3.1.dist-info/WHEEL
SiPM-2.3.1.dist-info/top_level.txt
SiPM-2.3.1.dist-info/RECORD
