Metadata-Version: 2.1
Name: SiPM
Version: 2.3.1
Summary: Library for Silicon Photomultipliers simulation.
Home-page: https://github.com/EdoPro98/SimSiPM
Author: Edoardo Proserpio
Author-email: edoardo.proserpio@gmail.com
Maintainer: Edoardo Proserpio
Maintainer-email: edoardo.proserpio@gmail.com
License: MIT
Platform: UNKNOWN
Classifier: Development Status :: 4 - Beta
Classifier: License :: OSI Approved :: MIT License
Classifier: Topic :: Scientific/Engineering :: Physics
Classifier: Programming Language :: Python :: 3
License-File: LICENSE
